{
  "prompt_id": "profile_update_main",
  "active_version": "2.0.0",
  "created_at": 1703123456,
  "last_updated": 1738454400,
  "description": "Main prompt for profile update extraction with comprehensive instructions and examples",
  "versions": {
    "1.0.0": {
      "created_at": 1703123456,
      "variables": ["profile_content_definition_prompt", "metadata_definition_prompt", "existing_profiles", "interactions"]
    },
    "1.0.1": {
      "created_at": 1764918197,
      "variables": ["profile_content_definition_prompt", "metadata_definition_prompt", "existing_profiles", "interactions"]
    },
    "2.0.0": {
      "created_at": 1738454400,
      "variables": ["existing_profiles", "interactions"],
      "changelog": "Moved stable instructions to system message, kept only dynamic data in user message for token caching"
    }
  }
}
